PIB/__init__.py
PIB/evaluation_tools/Folding.py
PIB/evaluation_tools/InverseFolding.py
PIB/evaluation_tools/__init__.py
PIB/evaluation_tools/design_interface.py
PIB/evaluation_tools/tools.py
PIB/src/__init__.py
PIB/src/version.py
PIB/src/datasets/__init__.py
PIB/src/datasets/alphafold_dataset.py
PIB/src/datasets/casp_dataset.py
PIB/src/datasets/cath_dataset.py
PIB/src/datasets/dataloader.py
PIB/src/datasets/deploy_utils.py
PIB/src/datasets/fast_dataloader.py
PIB/src/datasets/featurizer.py
PIB/src/datasets/mpnn_dataset.py
PIB/src/datasets/protein_rna_dataset.py
PIB/src/datasets/ts_dataset.py
PIB/src/datasets/utils.py
PIB/src/interface/__init__.py
PIB/src/interface/data_interface.py
PIB/src/interface/model_interface.py
PIB/src/interface/pretrain_interface.py
PIB/src/models/E3PiFold_model.py
PIB/src/models/MemoryESM.py
PIB/src/models/MemoryESMIF.py
PIB/src/models/MemoryPiFold.py
PIB/src/models/MemoryTuning.py
PIB/src/models/PretrainESMIF_model.py
PIB/src/models/PretrainESM_model.py
PIB/src/models/PretrainPiFold_model.py
PIB/src/models/Tuning.py
PIB/src/models/__init__.py
PIB/src/models/alphadesign_model.py
PIB/src/models/esmif_model.py
PIB/src/models/gca_model.py
PIB/src/models/graphtrans_model.py
PIB/src/models/gvp_model.py
PIB/src/models/kwdesign_model.py
PIB/src/models/pifold_model.py
PIB/src/models/proteinmpnn_model.py
PIB/src/models/structgnn_model.py
PIB/src/models/uniif_model.py
PIB/src/modules/E3PiFold.py
PIB/src/modules/__init__.py
PIB/src/modules/alphadesign_module.py
PIB/src/modules/esmif_module.py
PIB/src/modules/gca_module.py
PIB/src/modules/graphtrans_module.py
PIB/src/modules/gvp_module.py
PIB/src/modules/pifold_module.py
PIB/src/modules/pifold_module_old.py
PIB/src/modules/proteinmpnn_module.py
PIB/src/modules/uniif_module.py
PIB/src/tools/__init__.py
PIB/src/tools/affine_utils.py
PIB/src/tools/config_utils.py
PIB/src/tools/design_utils.py
PIB/src/tools/logger.py
PIB/src/tools/main_utils.py
PIB/src/tools/utils.py
PIB/train/__init__.py
PInvBench-0.1.0.dist-info/METADATA
PInvBench-0.1.0.dist-info/WHEEL
PInvBench-0.1.0.dist-info/top_level.txt
PInvBench-0.1.0.dist-info/RECORD
