Metadata-Version: 2.1
Name: PInvBench
Version: 0.1.0
Summary: A brief description of your package
Home-page: https://github.com/A4Bio/ProteinInvBench.git
Author: Zhangyang Gao
Author-email: gaozhangyang@westlake.edu.cn
Classifier: Programming Language :: Python :: 3
Classifier: License :: OSI Approved :: MIT License
Classifier: Operating System :: OS Independent
Requires-Python: >=3.6
